seganndb_login-1.0.dist-info/METADATA
seganndb_login-1.0.dist-info/RECORD
seganndb_login-1.0.dist-info/metadata.json
seganndb_login-1.0.dist-info/DESCRIPTION.rst
seganndb_login-1.0.dist-info/top_level.txt
seganndb_login-1.0.dist-info/WHEEL
seganndb_login/events.py
seganndb_login/__init__.py
seganndb_login/exceptions.py
seganndb_login/views.py
seganndb_login/utility.py
seganndb_login/tests/__init__.py
seganndb_login/tests/functional/test_flow.py
seganndb_login/tests/functional/__init__.py
seganndb_login/tests/functional/test_utility.py
seganndb_login/tests/unittests/test_views.py
seganndb_login/tests/unittests/__init__.py
seganndb_login/tests/unittests/test_init.py
seganndb_login/static/login.css
seganndb_login/static/pure-min.css
seganndb_login/templates/signin.mako
