Metadata-Version: 2.0
Name: seganndb-login
Version: 1.0
Summary: Pyramid login module for SegAnnDB login
Home-page: https://github.com/abstatic/SegAnnDB-login
Author: Abhishek Shrivastava
Author-email: x.abhishek.flyhigh@gmail.com
License: BSD-derived (http://www.repoze.org/LICENSE.txt)
Keywords: wsgi pylons pyramid auth authentication debug
Platform: UNKNOWN
Classifier: Development Status :: 4 - Beta
Classifier: Intended Audience :: Developers
Classifier: Programming Language :: Python
Classifier: Programming Language :: Python :: 2
Classifier: Programming Language :: Python :: 2.7
Classifier: Framework :: Pyramid
Classifier: Topic :: Internet :: WWW/HTTP :: WSGI
Requires-Dist: pyramid_mako
Requires-Dist: requests
